mercury_cli/__init__.py
mercury_cli/__main__.py
mercury_cli/main.py
mercury_cli/commands/__init__.py
mercury_cli/commands/automations/__init__.py
mercury_cli/commands/automations/automations.py
mercury_cli/commands/bulk/__init__.py
mercury_cli/commands/bulk/bulk.py
mercury_cli/commands/bulk/create.py
mercury_cli/commands/bulk/delete.py
mercury_cli/commands/bulk/modify.py
mercury_cli/commands/misc/__init__.py
mercury_cli/commands/misc/help.py
mercury_cli/commands/misc/plugins.py
mercury_cli/commands/misc/utils.py
mercury_cli/globals/__init__.py
mercury_cli/globals/cli.py
mercury_cli/tests/test_cli.py
mercury_cli/tests/test_commands.py
mercury_cli/utils/__init__.py
mercury_cli/utils/egg.py
mercury_cli/utils/service_group_id_callable.py
mercury_cli-1.0.0.dist-info/licenses/LICENSE
mercury_cli-1.0.0.dist-info/METADATA
mercury_cli-1.0.0.dist-info/WHEEL
mercury_cli-1.0.0.dist-info/entry_points.txt
mercury_cli-1.0.0.dist-info/top_level.txt
mercury_cli-1.0.0.dist-info/RECORD
