Metadata-Version: 2.4
Name: mercury-cli
Version: 1.0.0
Summary: A CLI wrapper for Mercury-OCIP
Author-email: Jordan Prescott <devteam@fourteenip.com>, Michael Clarke <devteam@fourteenip.com>, Billy Kelly <devteam@fourteenip.com>
Requires-Python: >=3.12
License-File: LICENSE
Requires-Dist: prompt-toolkit>=3.0.52
Requires-Dist: argparse>=1.4.0
Requires-Dist: asciimatics>=1.15.0
Requires-Dist: fourteen-prompt-toolkit-action-completer>=1.2.2
Requires-Dist: rich>=14.2.0
Requires-Dist: mercury-ocip>=1.1.0b0
Dynamic: license-file
